{
  "averages": {
    "humidity": 60,
    "moisture": 0,
    "temperature": 25
  },
  "config": {
    "thresholds": {
      "humidityWarn": 50,
      "moistureWarn": 40,
      "tempOff": 35,
      "tempOn": 36,
      "temperatureWarn": 25
    },
    "thresholds_updated": 1777857581
  },
  "control": {
    "relay": false
  },
  "sensors": {
    "zone-1": {
      "humidity": 60,
      "moisture": 19.54,
      "temperature": 25,
      "updatedAt": 4036070752
    },
    "zone-2": {
      "humidity": 60,
      "moisture": 19.54,
      "temperature": 25,
      "updatedAt": 4036038752
    },
    "zone-3": {
      "humidity": 60,
      "moisture": 19.54,
      "temperature": 25,
      "updatedAt": 4036038752
    }
  }
}